yoel_best/__init__.py
yoel_ar_bast_paketet-0.0.1.dist-info/METADATA
yoel_ar_bast_paketet-0.0.1.dist-info/WHEEL
yoel_ar_bast_paketet-0.0.1.dist-info/top_level.txt
yoel_ar_bast_paketet-0.0.1.dist-info/RECORD
