Metadata-Version: 2.4
Name: yoel-ar-bast-paketet
Version: 0.0.1
Summary: Ett paket som vet vem som är bäst
Author-email: Yoel <din.email@exempel.se>
Classifier: Programming Language :: Python :: 3
Classifier: Operating System :: OS Independent
Requires-Python: >=3.7
